ragguard/__init__.py
ragguard/circuit_breaker.py
ragguard/cli.py
ragguard/config.py
ragguard/connection_pool.py
ragguard/constants.py
ragguard/errors.py
ragguard/exceptions.py
ragguard/health.py
ragguard/logging.py
ragguard/py.typed
ragguard/retrievers_async.py
ragguard/retry.py
ragguard/types.py
ragguard/utils.py
ragguard/validation.py
ragguard/audit/__init__.py
ragguard/audit/logger.py
ragguard/filters/__init__.py
ragguard/filters/base.py
ragguard/filters/builder.py
ragguard/filters/builder_base.py
ragguard/filters/cache.py
ragguard/filters/custom.py
ragguard/filters/backends/__init__.py
ragguard/filters/backends/arangodb.py
ragguard/filters/backends/azure_search.py
ragguard/filters/backends/chromadb.py
ragguard/filters/backends/elasticsearch.py
ragguard/filters/backends/milvus.py
ragguard/filters/backends/neo4j.py
ragguard/filters/backends/neptune.py
ragguard/filters/backends/pgvector.py
ragguard/filters/backends/pinecone.py
ragguard/filters/backends/qdrant.py
ragguard/filters/backends/tigergraph.py
ragguard/filters/backends/weaviate.py
ragguard/integrations/__init__.py
ragguard/integrations/a2a.py
ragguard/integrations/autogen.py
ragguard/integrations/aws_bedrock.py
ragguard/integrations/crewai.py
ragguard/integrations/dspy.py
ragguard/integrations/langchain.py
ragguard/integrations/langgraph.py
ragguard/integrations/llamaindex.py
ragguard/integrations/mcp.py
ragguard/integrations/openai_assistants.py
ragguard/plugins/__init__.py
ragguard/plugins/base.py
ragguard/plugins/registry.py
ragguard/policy/__init__.py
ragguard/policy/engine.py
ragguard/policy/errors.py
ragguard/policy/explainer.py
ragguard/policy/models.py
ragguard/policy/parser.py
ragguard/policy/resolvers.py
ragguard/policy/validator.py
ragguard/policy/compiler/__init__.py
ragguard/policy/compiler/condition_compiler.py
ragguard/policy/compiler/evaluator.py
ragguard/policy/compiler/models.py
ragguard/retrievers/__init__.py
ragguard/retrievers/arangodb.py
ragguard/retrievers/azure_search.py
ragguard-0.3.1.dist-info/licenses/LICENSE
ragguard-0.3.1.dist-info/METADATA
ragguard-0.3.1.dist-info/WHEEL
ragguard-0.3.1.dist-info/entry_points.txt
ragguard-0.3.1.dist-info/top_level.txt
ragguard-0.3.1.dist-info/RECORD
