Metadata-Version: 2.4
Name: ragguard
Version: 0.3.1
Summary: Permission-aware retrieval for RAG applications
Author: RAGGuard Contributors
License: Apache-2.0
Project-URL: Homepage, https://github.com/maximus242/ragguard
Project-URL: Documentation, https://github.com/maximus242/ragguard#readme
Project-URL: Repository, https://github.com/maximus242/ragguard
Keywords: rag,retrieval,permissions,security,vector-database
Classifier: Development Status :: 4 - Beta
Classifier: Intended Audience :: Developers
Classifier: License :: OSI Approved :: Apache Software License
Classifier: Programming Language :: Python :: 3
Classifier: Programming Language :: Python :: 3.9
Classifier: Programming Language :: Python :: 3.10
Classifier: Programming Language :: Python :: 3.11
Classifier: Programming Language :: Python :: 3.12
Classifier: Topic :: Security
Classifier: Topic :: Database
Classifier: Topic :: Scientific/Engineering :: Artificial Intelligence
Classifier: Typing :: Typed
Requires-Python: >=3.9
License-File: LICENSE
Requires-Dist: pydantic>=2.0
Requires-Dist: pyyaml>=6.0
Provides-Extra: qdrant
Requires-Dist: qdrant-client>=1.7; extra == "qdrant"
Provides-Extra: pgvector
Requires-Dist: psycopg2-binary>=2.9; extra == "pgvector"
Requires-Dist: pgvector>=0.2; extra == "pgvector"
Provides-Extra: weaviate
Requires-Dist: weaviate-client>=3.0; extra == "weaviate"
Provides-Extra: pinecone
Requires-Dist: pinecone>=5.0.0; extra == "pinecone"
Provides-Extra: chromadb
Requires-Dist: chromadb>=0.4.0; extra == "chromadb"
Provides-Extra: milvus
Requires-Dist: pymilvus>=2.3.0; extra == "milvus"
Provides-Extra: faiss
Requires-Dist: faiss-cpu>=1.7.4; extra == "faiss"
Provides-Extra: elasticsearch
Requires-Dist: elasticsearch>=8.0.0; extra == "elasticsearch"
Provides-Extra: opensearch
Requires-Dist: opensearch-py>=2.0.0; extra == "opensearch"
Provides-Extra: azure
Requires-Dist: azure-search-documents>=11.4.0; extra == "azure"
Provides-Extra: neo4j
Requires-Dist: neo4j>=5.0.0; extra == "neo4j"
Provides-Extra: neptune
Requires-Dist: gremlinpython>=3.6.0; extra == "neptune"
Provides-Extra: tigergraph
Requires-Dist: pyTigerGraph>=1.0.0; extra == "tigergraph"
Provides-Extra: arangodb
Requires-Dist: python-arango>=7.0.0; extra == "arangodb"
Provides-Extra: langchain
Requires-Dist: langchain>=0.1.0; extra == "langchain"
Requires-Dist: langchain-core>=0.1.0; extra == "langchain"
Provides-Extra: llamaindex
Requires-Dist: llama-index>=0.9.0; extra == "llamaindex"
Provides-Extra: crewai
Requires-Dist: crewai>=0.28.0; extra == "crewai"
Provides-Extra: autogen
Requires-Dist: pyautogen>=0.2.0; extra == "autogen"
Provides-Extra: dspy
Requires-Dist: dspy-ai>=2.0.0; extra == "dspy"
Provides-Extra: google
Requires-Dist: google-auth>=2.0; extra == "google"
Requires-Dist: google-auth-oauthlib>=1.0; extra == "google"
Requires-Dist: google-auth-httplib2>=0.1; extra == "google"
Requires-Dist: google-api-python-client>=2.0; extra == "google"
Provides-Extra: all
Requires-Dist: qdrant-client>=1.7; extra == "all"
Requires-Dist: psycopg2-binary>=2.9; extra == "all"
Requires-Dist: pgvector>=0.2; extra == "all"
Requires-Dist: weaviate-client>=3.0; extra == "all"
Requires-Dist: pinecone>=5.0.0; extra == "all"
Requires-Dist: chromadb>=0.4.0; extra == "all"
Requires-Dist: pymilvus>=2.3.0; extra == "all"
Requires-Dist: faiss-cpu>=1.7.4; extra == "all"
Requires-Dist: elasticsearch>=8.0.0; extra == "all"
Requires-Dist: opensearch-py>=2.0.0; extra == "all"
Requires-Dist: azure-search-documents>=11.4.0; extra == "all"
Requires-Dist: neo4j>=5.0.0; extra == "all"
Requires-Dist: gremlinpython>=3.6.0; extra == "all"
Requires-Dist: pyTigerGraph>=1.0.0; extra == "all"
Requires-Dist: python-arango>=7.0.0; extra == "all"
Requires-Dist: langchain>=0.1.0; extra == "all"
Requires-Dist: langchain-core>=0.1.0; extra == "all"
Requires-Dist: llama-index>=0.9.0; extra == "all"
Requires-Dist: crewai>=0.28.0; extra == "all"
Requires-Dist: pyautogen>=0.2.0; extra == "all"
Requires-Dist: dspy-ai>=2.0.0; extra == "all"
Requires-Dist: google-auth>=2.0; extra == "all"
Requires-Dist: google-auth-oauthlib>=1.0; extra == "all"
Requires-Dist: google-auth-httplib2>=0.1; extra == "all"
Requires-Dist: google-api-python-client>=2.0; extra == "all"
Provides-Extra: dev
Requires-Dist: pytest>=7.0; extra == "dev"
Requires-Dist: pytest-asyncio>=0.23; extra == "dev"
Requires-Dist: pytest-cov>=4.0; extra == "dev"
Requires-Dist: mypy>=1.8.0; extra == "dev"
Requires-Dist: ruff>=0.1.0; extra == "dev"
Requires-Dist: bandit>=1.7.0; extra == "dev"
Requires-Dist: types-PyYAML>=6.0; extra == "dev"
Requires-Dist: types-requests>=2.31; extra == "dev"
Dynamic: license-file
